bibkit/__init__.py
bibkit/identifiers/__init__.py
bibkit/identifiers/doi.py
bibkit/utils.py
bibkit-0.2.2.dist-info/LICENSE
bibkit-0.2.2.dist-info/WHEEL
bibkit-0.2.2.dist-info/METADATA
bibkit-0.2.2.dist-info/RECORD
