Metadata-Version: 2.1
Name: bibkit
Version: 0.2.2
Summary: A collection of tools for coding librarians and coders in libraries
Home-page: https://codeberg.org/tt/bibkit
License: GPL-3.0-or-later
Author: Daniel Opitz
Author-email: daniel@toilandtrouble.de
Requires-Python: >=3.8,<4.0
Classifier: License :: OSI Approved :: GNU General Public License v3 or later (GPLv3+)
Classifier: Programming Language :: Python :: 3
Classifier: Programming Language :: Python :: 3.8
Classifier: Programming Language :: Python :: 3.9
Classifier: Programming Language :: Python :: 3.10
Classifier: Programming Language :: Python :: 3.11
Project-URL: Repository, https://codeberg.org/tt/bibkit
